[{"date":"2021.09.03 10:27:31","location":"KIRIK-DOMANIC (KUTAHYA)","lat":"39.7122","lng":"29.5523","mag":"1.5","depth":"10.1"},{"date":"2021.09.03 11:37:06","location":"GELEMIS-KAS (ANTALYA)","lat":"36.2382","lng":"29.2068","mag":"1.8","depth":"22.6"},{"date":"2021.09.03 12:18:17","location":"KOCABAS-HONAZ (DENIZLI)","lat":"37.8547","lng":"29.3325","mag":"3.6","depth":"1.6"},{"date":"2021.09.03 12:35:52","location":"LETAFET-ORHANELI (BURSA)","lat":"39.8903","lng":"28.7702","mag":"2.1","depth":"0.0"},{"date":"2021.09.03 13:14:23","location":"BUYUKECELI-GULNAR (MERSIN)","lat":"36.1393","lng":"33.5682","mag":"0.9","depth":"0.0"},{"date":"2021.09.03 13:29:07","location":"AZERBAYCAN","lat":"41.1023","lng":"43.8945","mag":"3.8","depth":"2.0"},{"date":"2021.09.03 14:44:48","location":"AKDENIZ","lat":"36.3620","lng":"27.0823","mag":"2.1","depth":"12.9"},{"date":"2021.09.03 14:55:19","location":"ONIKI ADALAR (AKDENIZ)","lat":"36.4142","lng":"27.1710","mag":"2.0","depth":"14.4"},{"date":"2021.09.03 15:00:05","location":"AKDENIZ","lat":"36.3112","lng":"27.1178","mag":"2.2","depth":"8.4"},{"date":"2021.09.03 15:14:25","location":"YARHISAR-(NIGDE)","lat":"38.0515","lng":"34.9400","mag":"1.9","depth":"10.1"},{"date":"2021.09.03 15:56:30","location":"DELIALIUSAGI-YAHYALI (KAYSERI)","lat":"37.9608","lng":"35.5952","mag":"1.8","depth":"12.5"},{"date":"2021.09.03 17:32:27","location":"PIRAHMETLER-(BOLU)","lat":"40.7853","lng":"31.5633","mag":"1.9","depth":"0.0"},{"date":"2021.09.03 17:50:31","location":"GIRIT ADASI (AKDENIZ)","lat":"35.3268","lng":"23.3783","mag":"2.5","depth":"14.4"},{"date":"2021.09.03 17:54:35","location":"AKDENIZ","lat":"36.3638","lng":"27.0807","mag":"2.3","depth":"9.4"},{"date":"2021.09.03 17:54:37","location":"LEYLEKLI-EMIRDAG (AFYONKARAHISAR)","lat":"38.7980","lng":"31.4343","mag":"1.4","depth":"12.8"},{"date":"2021.09.03 18:19:19","location":"GIRIT ADASI (AKDENIZ)","lat":"35.1853","lng":"25.1508","mag":"2.1","depth":"17.5"},{"date":"2021.09.03 18:20:06","location":"AKDENIZ","lat":"36.3150","lng":"28.8347","mag":"2.3","depth":"14.8"},{"date":"2021.09.03 18:50:30","location":"AKDENIZ","lat":"35.9740","lng":"26.9037","mag":"2.8","depth":"8.0"},{"date":"2021.09.03 19:08:42","location":"YUNANISTAN","lat":"39.8162","lng":"23.5362","mag":"2.7","depth":"38.2"},{"date":"2021.09.03 21:29:39","location":"AKDENIZ","lat":"36.3310","lng":"27.0218","mag":"1.9","depth":"7.3"},{"date":"2021.09.03 21:35:03","location":"GIRIT ADASI ACIKLARI (AKDENIZ)","lat":"34.6728","lng":"24.9963","mag":"1.9","depth":"14.7"},{"date":"2021.09.03 23:03:20","location":"SISAM ADASI (EGE DENIZI)","lat":"37.7540","lng":"26.8858","mag":"2.0","depth":"8.2"},{"date":"2021.09.03 23:34:36","location":"GIRIT ADASI (AKDENIZ)","lat":"35.0163","lng":"23.4702","mag":"2.4","depth":"26.7"},{"date":"2021.09.03 23:50:15","location":"AGIN (ELAZIG)","lat":"38.9437","lng":"38.7387","mag":"1.7","depth":"5.4"},{"date":"2021.09.03 23:58:24","location":"MIDILLI ADASI GUNEYI (EGE DENIZI)","lat":"38.9263","lng":"25.9140","mag":"2.5","depth":"9.6"},{"date":"2021.09.03 23:58:58","location":"ONIKI ADALAR (AKDENIZ)","lat":"36.4313","lng":"27.0697","mag":"1.8","depth":"5.0"},{"date":"2021.09.04 01:41:58","location":"GEBELER-KIRKAGAC (MANISA)","lat":"39.1580","lng":"27.8198","mag":"1.9","depth":"12.4"},{"date":"2021.09.04 01:42:32","location":"KUSADASI KORFEZI (EGE DENIZI)","lat":"37.7985","lng":"27.0842","mag":"1.4","depth":"29.2"},{"date":"2021.09.04 02:37:04","location":"AKDENIZ","lat":"36.7800","lng":"26.4867","mag":"2.0","depth":"5.0"},{"date":"2021.09.04 02:45:30","location":"ONIKI ADALAR (AKDENIZ)","lat":"36.4782","lng":"27.1908","mag":"2.9","depth":"10.3"},{"date":"2021.09.04 02:56:27","location":"SISAM ADASI (EGE DENIZI)","lat":"37.7393","lng":"26.8460","mag":"1.5","depth":"20.6"},{"date":"2021.09.04 02:57:43","location":"BESKARIS-ALTINTAS (KUTAHYA)","lat":"38.9877","lng":"30.1822","mag":"2.1","depth":"5.2"},{"date":"2021.09.04 03:01:34","location":"GIRIT ADASI (AKDENIZ)","lat":"35.2587","lng":"25.2368","mag":"2.2","depth":"5.0"},{"date":"2021.09.04 04:31:55","location":"MACUN-POLATLI (ANKARA)","lat":"39.6380","lng":"32.3418","mag":"1.9","depth":"1.9"},{"date":"2021.09.04 05:39:49","location":"ONIKI ADALAR (AKDENIZ)","lat":"36.4958","lng":"27.1805","mag":"2.1","depth":"12.6"},{"date":"2021.09.04 05:48:35","location":"ONIKI ADALAR (AKDENIZ)","lat":"36.4783","lng":"27.1695","mag":"2.0","depth":"5.0"},{"date":"2021.09.04 05:56:42","location":"KUSADASI KORFEZI (EGE DENIZI)","lat":"37.8485","lng":"26.8768","mag":"1.4","depth":"11.4"},{"date":"2021.09.04 06:58:20","location":"BADEMLI-AGIN (ELAZIG)","lat":"39.0112","lng":"38.6368","mag":"2.3","depth":"10.0"},{"date":"2021.09.04 08:45:17","location":"ATADAMI-DIYADIN (AGRI)","lat":"39.3357","lng":"43.8653","mag":"2.8","depth":"11.3"},{"date":"2021.09.04 08:56:39","location":"AKDENIZ","lat":"35.6625","lng":"27.0767","mag":"1.9","depth":"3.4"},{"date":"2021.09.04 09:04:20","location":"UCKUYU-SULTANDAGI (AFYONKARAHISAR)","lat":"38.5762","lng":"31.4565","mag":"2.4","depth":"5.5"}]