[{"date":"2022.09.03 20:16:14","location":"YUNANISTAN","lat":"35.8403","lng":"22.0032","mag":"4.4","depth":"5.0"},{"date":"2022.09.03 20:50:15","location":"BOLAY-TASKENT (KONYA)","lat":"36.8458","lng":"32.5608","mag":"1.8","depth":"16.7"},{"date":"2022.09.03 21:09:23","location":"KIRAN-(MUGLA)","lat":"37.0448","lng":"28.1728","mag":"1.0","depth":"16.6"},{"date":"2022.09.03 21:15:39","location":"KUSADASI KORFEZI (EGE DENIZI)","lat":"37.9660","lng":"27.1568","mag":"1.3","depth":"12.5"},{"date":"2022.09.03 23:10:34","location":"PINARLAR-TAVAS (DENIZLI)","lat":"37.5260","lng":"29.0918","mag":"1.3","depth":"2.7"},{"date":"2022.09.03 23:51:52","location":"SELIMIYE-MARMARIS (MUGLA)","lat":"36.7467","lng":"28.0302","mag":"1.0","depth":"29.0"},{"date":"2022.09.04 00:03:14","location":"BEYDILI-(CORUM)","lat":"40.6428","lng":"34.8858","mag":"2.6","depth":"6.4"},{"date":"2022.09.04 00:14:32","location":"PEKMEZCI-AKHISAR (MANISA)","lat":"39.0143","lng":"27.9963","mag":"1.9","depth":"5.1"},{"date":"2022.09.04 02:06:07","location":"YEMISENDERE-(MUGLA)","lat":"37.2220","lng":"28.5638","mag":"1.2","depth":"5.3"},{"date":"2022.09.04 02:33:12","location":"CEPNI-BANDIRMA (BALIKESIR)","lat":"40.2507","lng":"27.8695","mag":"2.0","depth":"7.4"},{"date":"2022.09.04 03:05:45","location":"AKDENIZ","lat":"36.2375","lng":"28.9928","mag":"1.4","depth":"8.0"},{"date":"2022.09.04 03:31:51","location":"GOLCUK-ULA (MUGLA)","lat":"37.1397","lng":"28.5328","mag":"0.8","depth":"29.2"},{"date":"2022.09.04 03:49:18","location":"UMUTLU-TASOVA (AMASYA)","lat":"40.7675","lng":"36.4668","mag":"3.7","depth":"4.4"},{"date":"2022.09.04 03:58:32","location":"YALI-BODRUM (MUGLA)","lat":"36.9858","lng":"27.3658","mag":"2.9","depth":"11.4"},{"date":"2022.09.04 04:23:28","location":"KUSADASI KORFEZI (EGE DENIZI)","lat":"37.8722","lng":"27.1673","mag":"1.0","depth":"8.1"},{"date":"2022.09.04 05:02:11","location":"GOKOVA KORFEZI (AKDENIZ)","lat":"36.9722","lng":"27.3837","mag":"1.8","depth":"6.5"},{"date":"2022.09.04 05:03:48","location":"GOKOVA-ULA (MUGLA)","lat":"37.0495","lng":"28.3692","mag":"1.0","depth":"23.6"},{"date":"2022.09.04 05:10:59","location":"AKYAR-KORKUTELI (ANTALYA)","lat":"37.1298","lng":"30.1905","mag":"1.1","depth":"9.7"},{"date":"2022.09.04 05:15:00","location":"GOKOVA KORFEZI (AKDENIZ)","lat":"37.0047","lng":"27.5170","mag":"1.3","depth":"1.4"},{"date":"2022.09.04 05:25:42","location":"CUBUKCU-SAMANDAG (HATAY)","lat":"36.1928","lng":"36.0233","mag":"1.2","depth":"5.0"},{"date":"2022.09.04 06:10:51","location":"KUSADASI KORFEZI (EGE DENIZI)","lat":"37.9615","lng":"27.1278","mag":"1.6","depth":"7.4"},{"date":"2022.09.04 07:01:27","location":"MARMARA DENIZI","lat":"40.7797","lng":"27.7260","mag":"1.8","depth":"17.8"},{"date":"2022.09.04 07:20:52","location":"AKDENIZ","lat":"35.7335","lng":"26.8112","mag":"1.9","depth":"8.2"},{"date":"2022.09.04 07:48:59","location":"CAMLIK-BODRUM (MUGLA)","lat":"37.0680","lng":"27.4955","mag":"1.6","depth":"17.1"},{"date":"2022.09.04 08:27:37","location":"SISAM ADASI (EGE DENIZI)","lat":"37.6463","lng":"26.7167","mag":"1.9","depth":"11.1"},{"date":"2022.09.04 09:21:52","location":"CAMKOY-GOLHISAR (BURDUR)","lat":"37.2817","lng":"29.5123","mag":"1.4","depth":"5.3"},{"date":"2022.09.04 10:20:07","location":"BOGAZCIFTLIK-BULDAN (DENIZLI)","lat":"38.1927","lng":"28.8555","mag":"1.5","depth":"14.1"},{"date":"2022.09.04 10:22:41","location":"KELLECI-BABADAG (DENIZLI)","lat":"37.8097","lng":"28.8977","mag":"1.7","depth":"9.1"},{"date":"2022.09.04 10:32:49","location":"KARAKOY-BULDAN (DENIZLI)","lat":"38.2140","lng":"28.8862","mag":"2.5","depth":"6.4"},{"date":"2022.09.04 10:36:23","location":"CARIKSIZ-EZINE (CANAKKALE)","lat":"39.7112","lng":"26.3960","mag":"1.8","depth":"12.4"},{"date":"2022.09.04 11:56:30","location":"KUSADASI KORFEZI (EGE DENIZI)","lat":"37.9968","lng":"27.1573","mag":"1.8","depth":"2.9"},{"date":"2022.09.04 12:31:08","location":"KARAYAVSAN-POLATLI (ANKARA)","lat":"39.4882","lng":"32.3507","mag":"1.9","depth":"0.0"},{"date":"2022.09.04 13:01:36","location":"EGE DENIZI","lat":"37.5697","lng":"26.7630","mag":"2.1","depth":"5.1"},{"date":"2022.09.04 17:25:53","location":"EGE DENIZI","lat":"37.6498","lng":"26.8193","mag":"1.8","depth":"6.8"},{"date":"2022.09.04 18:14:41","location":"CICEKLI-ULA (MUGLA)","lat":"37.0965","lng":"28.5057","mag":"2.6","depth":"6.7"},{"date":"2022.09.04 18:17:43","location":"ARMUTCUK-ULA (MUGLA)","lat":"37.1098","lng":"28.5147","mag":"2.0","depth":"6.0"},{"date":"2022.09.04 19:00:37","location":"KUSADASI KORFEZI (EGE DENIZI)","lat":"37.9862","lng":"27.1988","mag":"2.1","depth":"4.1"}]