[{"date":"2021.01.14 14:10:30","location":"BUYUKECELI-GULNAR (MERSIN)","lat":"36.1378","lng":"33.5600","mag":"1.0","depth":"0.0"},{"date":"2021.01.14 14:30:14","location":"EGE DENIZI","lat":"37.8813","lng":"26.7565","mag":"2.8","depth":"8.1"},{"date":"2021.01.14 14:41:04","location":"EGE DENIZI","lat":"37.8365","lng":"26.8142","mag":"1.9","depth":"11.2"},{"date":"2021.01.14 15:28:40","location":"KUSADASI KORFEZI (EGE DENIZI)","lat":"37.9257","lng":"27.1123","mag":"1.8","depth":"2.6"},{"date":"2021.01.14 15:45:52","location":"ORTAKENTYAHSI-BODRUM (MUGLA)","lat":"37.0643","lng":"27.3527","mag":"1.1","depth":"4.7"},{"date":"2021.01.14 16:07:14","location":"KARAHUSEYIN-KALE (MALATYA)","lat":"38.3565","lng":"38.8952","mag":"2.0","depth":"8.6"},{"date":"2021.01.14 16:58:24","location":"KUSADASI KORFEZI (EGE DENIZI)","lat":"37.8980","lng":"26.9722","mag":"1.6","depth":"4.2"},{"date":"2021.01.14 18:02:28","location":"KUSADASI KORFEZI (EGE DENIZI)","lat":"38.0108","lng":"27.0325","mag":"1.8","depth":"21.7"},{"date":"2021.01.14 19:00:22","location":"DILEKTEPE-SOLHAN (BINGOL)","lat":"38.9537","lng":"40.9872","mag":"1.9","depth":"5.7"},{"date":"2021.01.14 19:40:09","location":"KUSADASI KORFEZI (EGE DENIZI)","lat":"37.8478","lng":"27.0315","mag":"1.9","depth":"6.5"},{"date":"2021.01.14 21:18:20","location":"GOKCEKANAT-(BINGOL)","lat":"38.9717","lng":"40.3305","mag":"1.9","depth":"7.6"},{"date":"2021.01.14 21:52:58","location":"KIRMIZILAR-(BALIKESIR)","lat":"39.7985","lng":"27.7987","mag":"1.8","depth":"7.8"},{"date":"2021.01.14 21:56:27","location":"BEKCITEPE-SIVRICE (ELAZIG)","lat":"38.5015","lng":"39.2755","mag":"2.4","depth":"5.0"},{"date":"2021.01.14 22:22:16","location":"BEKCITEPE-SIVRICE (ELAZIG)","lat":"38.4823","lng":"39.2853","mag":"1.9","depth":"5.3"},{"date":"2021.01.14 23:13:24","location":"KARAAGAC-FETHIYE (MUGLA)","lat":"36.4992","lng":"29.1802","mag":"2.3","depth":"19.0"},{"date":"2021.01.14 23:25:09","location":"ESKIOREN-(CORUM)","lat":"40.5878","lng":"34.5822","mag":"1.6","depth":"14.2"},{"date":"2021.01.14 23:31:04","location":"MOLLAKASIM-(VAN)","lat":"38.6938","lng":"43.1118","mag":"2.4","depth":"5.0"},{"date":"2021.01.14 23:43:36","location":"SISAM ADASI (EGE DENIZI)","lat":"37.8205","lng":"26.8493","mag":"1.7","depth":"22.4"},{"date":"2021.01.14 23:58:29","location":"SISAM ADASI (EGE DENIZI)","lat":"37.8182","lng":"26.8627","mag":"1.2","depth":"15.4"},{"date":"2021.01.15 00:04:02","location":"KUSADASI KORFEZI (EGE DENIZI)","lat":"37.9408","lng":"27.1803","mag":"1.5","depth":"15.8"},{"date":"2021.01.15 00:04:22","location":"VAN GOLU","lat":"38.6175","lng":"42.8345","mag":"1.8","depth":"8.3"},{"date":"2021.01.15 00:24:55","location":"CAKIRBEY-(VAN)","lat":"38.9045","lng":"43.5953","mag":"2.0","depth":"2.8"},{"date":"2021.01.15 00:34:22","location":"EGE DENIZI","lat":"37.8842","lng":"26.7293","mag":"1.3","depth":"2.6"},{"date":"2021.01.15 00:35:22","location":"KARAAGAC-FETHIYE (MUGLA)","lat":"36.4562","lng":"29.1533","mag":"1.7","depth":"19.5"},{"date":"2021.01.15 01:54:43","location":"SISAM ADASI (EGE DENIZI)","lat":"37.7053","lng":"26.7507","mag":"1.8","depth":"7.9"},{"date":"2021.01.15 02:17:30","location":"AKSU-GOLYAKA (DUZCE)","lat":"40.7655","lng":"30.9582","mag":"1.6","depth":"10.9"},{"date":"2021.01.15 02:44:04","location":"ESKIBALTA-YEDISU (BINGOL)","lat":"39.4228","lng":"40.4230","mag":"1.7","depth":"5.0"},{"date":"2021.01.15 02:49:28","location":"KAVAKTEPE-(ELAZIG)","lat":"38.5000","lng":"39.2255","mag":"2.3","depth":"1.9"},{"date":"2021.01.15 02:58:23","location":"COGMEN-DALAMAN (MUGLA)","lat":"36.8495","lng":"29.0343","mag":"3.0","depth":"5.0"},{"date":"2021.01.15 03:15:06","location":"BASKAYNAK-SIVRICE (ELAZIG)","lat":"38.3960","lng":"39.3740","mag":"1.3","depth":"5.8"},{"date":"2021.01.15 03:18:13","location":"YENICE-CAMOLUK (GIRESUN)","lat":"40.0730","lng":"38.8960","mag":"2.4","depth":"5.5"},{"date":"2021.01.15 03:23:13","location":"SISAM ADASI (EGE DENIZI)","lat":"37.8208","lng":"26.7028","mag":"1.6","depth":"23.0"},{"date":"2021.01.15 03:49:54","location":"KUSADASI KORFEZI (EGE DENIZI)","lat":"37.8643","lng":"26.9627","mag":"2.0","depth":"17.4"},{"date":"2021.01.15 04:09:25","location":"SISAM ADASI (EGE DENIZI)","lat":"37.8400","lng":"26.8815","mag":"1.6","depth":"14.6"},{"date":"2021.01.15 05:05:09","location":"BALPINARI-PUTURGE (MALATYA)","lat":"38.2592","lng":"38.7702","mag":"2.2","depth":"3.3"},{"date":"2021.01.15 06:40:04","location":"KUSADASI KORFEZI (EGE DENIZI)","lat":"37.9297","lng":"26.9930","mag":"1.6","depth":"11.4"},{"date":"2021.01.15 07:03:19","location":"CANAKCI-KALE (MALATYA)","lat":"38.3377","lng":"38.7938","mag":"1.9","depth":"5.0"},{"date":"2021.01.15 07:14:08","location":"EGE DENIZI","lat":"39.7287","lng":"25.7233","mag":"2.4","depth":"6.3"},{"date":"2021.01.15 08:03:28","location":"GOKOVA KORFEZI (AKDENIZ)","lat":"36.9332","lng":"28.0453","mag":"1.7","depth":"22.9"},{"date":"2021.01.15 08:52:34","location":"ESKIKOY-KALECIK (ANKARA)","lat":"40.0617","lng":"33.3283","mag":"2.5","depth":"3.3"},{"date":"2021.01.15 09:16:18","location":"URUNVEREN-(ELAZIG)","lat":"38.5253","lng":"39.1510","mag":"1.4","depth":"10.5"},{"date":"2021.01.15 09:49:56","location":"BOZARMUT-KANGAL (SIVAS)","lat":"39.2595","lng":"37.3195","mag":"1.6","depth":"5.0"},{"date":"2021.01.15 10:15:59","location":"SADIKKIRI-ALTINTAS (KUTAHYA)","lat":"39.1757","lng":"30.1082","mag":"1.2","depth":"5.0"},{"date":"2021.01.15 10:28:47","location":"SEYHZELIHA-(SANLIURFA)","lat":"37.3958","lng":"38.8407","mag":"1.7","depth":"5.0"},{"date":"2021.01.15 10:35:37","location":"YAGMURLU-KIRKAGAC (MANISA)","lat":"39.1678","lng":"27.7648","mag":"2.5","depth":"3.3"},{"date":"2021.01.15 10:52:01","location":"KOSEBAYIR-SIVRICE (ELAZIG)","lat":"38.3912","lng":"39.1883","mag":"1.9","depth":"7.5"},{"date":"2021.01.15 11:13:23","location":"HAYDARIYE-GEMLIK (BURSA)","lat":"40.5227","lng":"29.1595","mag":"1.3","depth":"0.0"},{"date":"2021.01.15 12:16:56","location":"KUSDOGAN-YESILYURT (MALATYA)","lat":"38.3433","lng":"38.1413","mag":"1.9","depth":"0.0"},{"date":"2021.01.15 12:28:48","location":"AFSAR-BALA (ANKARA)","lat":"39.4817","lng":"33.0660","mag":"2.0","depth":"15.1"},{"date":"2021.01.15 12:34:07","location":"KULTAK-MILAS (MUGLA)","lat":"37.0428","lng":"28.0632","mag":"1.9","depth":"5.0"},{"date":"2021.01.15 13:13:57","location":"MESELIK-TARSUS (MERSIN)","lat":"37.0670","lng":"34.7662","mag":"1.4","depth":"0.0"}]