[{"date":"2020.10.29 18:15:43","location":"GULPINAR ACIKLARI-CANAKKALE (EGE DENIZI)","lat":"39.4520","lng":"25.8792","mag":"2.1","depth":"5.0"},{"date":"2020.10.29 18:33:53","location":"GULPINAR ACIKLARI-CANAKKALE (EGE DENIZI)","lat":"39.4697","lng":"25.9268","mag":"2.7","depth":"2.5"},{"date":"2020.10.29 18:40:15","location":"SAHINYURDU-GEMLIK (BURSA)","lat":"40.4757","lng":"29.2062","mag":"1.8","depth":"0.0"},{"date":"2020.10.29 21:25:56","location":"ARIKONAK-SINCIK (ADIYAMAN)","lat":"38.1197","lng":"38.5732","mag":"3.3","depth":"5.0"},{"date":"2020.10.29 21:33:17","location":"GOZLUCE-TEKMAN (ERZURUM)","lat":"39.5720","lng":"41.3577","mag":"2.4","depth":"8.2"},{"date":"2020.10.29 22:11:08","location":"KARSIYAKA-ADILCEVAZ (BITLIS)","lat":"38.7730","lng":"42.9525","mag":"1.8","depth":"6.4"},{"date":"2020.10.30 03:16:00","location":"AYRANLI-NAZIMIYE (TUNCELI)","lat":"39.2377","lng":"39.8970","mag":"2.4","depth":"1.1"},{"date":"2020.10.30 03:34:23","location":"UNBULAK-TUZLUCA (IGDIR)","lat":"39.7887","lng":"43.4192","mag":"2.0","depth":"3.0"},{"date":"2020.10.30 03:36:40","location":"BILEK-(MUS)","lat":"39.0298","lng":"41.2192","mag":"2.5","depth":"6.9"},{"date":"2020.10.30 04:31:08","location":"GUZELYURT-CERKES (CANKIRI)","lat":"40.7407","lng":"33.0363","mag":"1.4","depth":"5.7"},{"date":"2020.10.30 04:59:49","location":"AKDENIZ","lat":"35.7167","lng":"31.0853","mag":"2.3","depth":"48.6"},{"date":"2020.10.30 05:11:13","location":"TALAS (KAYSERI)","lat":"38.7313","lng":"35.5643","mag":"1.7","depth":"5.0"},{"date":"2020.10.30 05:44:52","location":"EDREMIT KORFEZI (EGE DENIZI)","lat":"39.4010","lng":"26.3658","mag":"2.6","depth":"10.0"},{"date":"2020.10.30 06:14:57","location":"GUZELKOY ACIKLARI-TEKIRDAG (MARMARA DENIZI)","lat":"40.7442","lng":"27.3923","mag":"1.5","depth":"12.9"},{"date":"2020.10.30 06:31:59","location":"SEKKOY-MILAS (MUGLA)","lat":"37.1098","lng":"27.9007","mag":"1.5","depth":"5.3"},{"date":"2020.10.30 07:01:26","location":"AVDAN-AKOREN (KONYA)","lat":"37.3290","lng":"32.2650","mag":"1.9","depth":"10.9"},{"date":"2020.10.30 07:56:06","location":"GIRIT ADASI (AKDENIZ)","lat":"34.8940","lng":"24.1388","mag":"3.1","depth":"32.2"},{"date":"2020.10.30 08:08:20","location":"SAROS KORFEZI (EGE DENIZI)","lat":"40.4648","lng":"26.3878","mag":"1.4","depth":"18.1"},{"date":"2020.10.30 08:09:29","location":"EGILLER-BERGAMA (IZMIR)","lat":"39.2572","lng":"27.3552","mag":"2.1","depth":"6.2"},{"date":"2020.10.30 08:13:41","location":"UCOLUK-KONYAALTI (ANTALYA)","lat":"36.7027","lng":"30.4367","mag":"2.3","depth":"18.1"},{"date":"2020.10.30 08:54:13","location":"YALNIZKONAK-(AGRI)","lat":"39.7602","lng":"43.3645","mag":"2.0","depth":"28.1"},{"date":"2020.10.30 08:57:43","location":"PASAPINARI-(MUGLA)","lat":"37.2297","lng":"28.1857","mag":"1.6","depth":"0.0"},{"date":"2020.10.30 09:05:59","location":"AKDENIZ","lat":"35.7883","lng":"28.2018","mag":"2.4","depth":"6.2"},{"date":"2020.10.30 09:12:44","location":"AYVACIK-HAMUR (AGRI)","lat":"39.3255","lng":"43.1277","mag":"1.9","depth":"26.3"},{"date":"2020.10.30 09:18:31","location":"AKDENIZ","lat":"36.4208","lng":"28.7713","mag":"1.9","depth":"21.0"},{"date":"2020.10.30 11:48:01","location":"CUKURCA-(BINGOL)","lat":"38.9427","lng":"40.5018","mag":"4.0","depth":"2.1"},{"date":"2020.10.30 14:51:25","location":"EGE DENIZI","lat":"37.9020","lng":"26.7942","mag":"6.8","depth":"11.8"},{"date":"2020.10.30 14:53:54","location":"EGE DENIZI","lat":"37.8972","lng":"26.8287","mag":"4.5","depth":"8.6"},{"date":"2020.10.30 14:55:02","location":"KUSADASI KORFEZI (EGE DENIZI)","lat":"37.9663","lng":"27.0080","mag":"3.9","depth":"8.9"},{"date":"2020.10.30 14:56:02","location":"EGE DENIZI","lat":"37.9718","lng":"26.5832","mag":"3.8","depth":"7.3"},{"date":"2020.10.30 14:58:05","location":"KUSADASI KORFEZI (EGE DENIZI)","lat":"37.8775","lng":"26.8998","mag":"4.3","depth":"5.3"},{"date":"2020.10.30 14:59:29","location":"KUSADASI KORFEZI (EGE DENIZI)","lat":"37.8468","lng":"27.0112","mag":"4.1","depth":"8.1"},{"date":"2020.10.30 15:01:37","location":"KUSADASI KORFEZI (EGE DENIZI)","lat":"37.8417","lng":"26.9317","mag":"4.1","depth":"4.6"},{"date":"2020.10.30 15:13:29","location":"KUSADASI KORFEZI (EGE DENIZI)","lat":"37.8107","lng":"27.0130","mag":"4.0","depth":"11.5"},{"date":"2020.10.30 15:17:20","location":"SISAM ADASI (EGE DENIZI)","lat":"37.8332","lng":"26.6523","mag":"3.2","depth":"21.6"},{"date":"2020.10.30 15:19:09","location":"SISAM ADASI (EGE DENIZI)","lat":"37.7700","lng":"26.5202","mag":"4.0","depth":"8.6"},{"date":"2020.10.30 15:29:11","location":"KUSADASI KORFEZI (EGE DENIZI)","lat":"37.9205","lng":"26.9233","mag":"4.2","depth":"6.9"},{"date":"2020.10.30 15:29:49","location":"KUSADASI KORFEZI (EGE DENIZI)","lat":"37.9160","lng":"27.0238","mag":"4.2","depth":"6.4"},{"date":"2020.10.30 15:32:01","location":"SISAM ADASI (EGE DENIZI)","lat":"37.7813","lng":"26.8255","mag":"3.7","depth":"8.9"},{"date":"2020.10.30 15:33:20","location":"SISAM ADASI (EGE DENIZI)","lat":"37.8227","lng":"26.8302","mag":"4.1","depth":"2.5"},{"date":"2020.10.30 15:50:20","location":"SISAM ADASI (EGE DENIZI)","lat":"37.8297","lng":"26.8902","mag":"2.8","depth":"5.9"},{"date":"2020.10.30 15:51:13","location":"EGE DENIZI","lat":"37.9150","lng":"26.4600","mag":"3.2","depth":"24.1"},{"date":"2020.10.30 15:53:35","location":"EGE DENIZI","lat":"37.8330","lng":"26.8165","mag":"3.2","depth":"5.7"},{"date":"2020.10.30 15:56:33","location":"SISAM ADASI (EGE DENIZI)","lat":"37.8305","lng":"26.8985","mag":"3.2","depth":"7.1"},{"date":"2020.10.30 16:00:42","location":"EGE DENIZI","lat":"37.8378","lng":"26.7853","mag":"4.9","depth":"5.3"},{"date":"2020.10.30 16:06:57","location":"KUSADASI KORFEZI (EGE DENIZI)","lat":"37.8585","lng":"26.9967","mag":"4.2","depth":"6.2"},{"date":"2020.10.30 16:25:16","location":"EGE DENIZI","lat":"37.9292","lng":"26.7695","mag":"3.0","depth":"15.3"}]