[{"date":"2020.10.05 13:08:26","location":"DEREKOY-SOMA (MANISA)","lat":"39.1270","lng":"27.5722","mag":"1.8","depth":"0.0"},{"date":"2020.10.05 13:45:30","location":"OBRUK-BOR (NIGDE)","lat":"38.0023","lng":"34.0697","mag":"3.1","depth":"5.0"},{"date":"2020.10.05 13:55:13","location":"EGE DENIZI","lat":"38.0668","lng":"26.1482","mag":"2.0","depth":"5.0"},{"date":"2020.10.05 14:28:21","location":"AKDENIZ","lat":"35.7990","lng":"28.2220","mag":"2.6","depth":"8.2"},{"date":"2020.10.05 14:45:30","location":"KAYADERE-MILAS (MUGLA)","lat":"37.2115","lng":"27.9112","mag":"1.4","depth":"0.0"},{"date":"2020.10.05 14:53:37","location":"SILIVRI ACIKLARI-ISTANBUL (MARMARA DENIZI)","lat":"40.8558","lng":"28.2523","mag":"1.7","depth":"5.4"},{"date":"2020.10.05 15:39:38","location":"HAYRANLAR-MENGEN (BOLU)","lat":"40.9153","lng":"31.8092","mag":"1.7","depth":"13.0"},{"date":"2020.10.05 16:00:54","location":"SALHANE-CALDIRAN (VAN)","lat":"39.0208","lng":"43.9462","mag":"2.1","depth":"3.5"},{"date":"2020.10.05 16:13:27","location":"KECIKALESI-ALTUNHISAR (NIGDE)","lat":"38.0392","lng":"34.1332","mag":"2.2","depth":"1.9"},{"date":"2020.10.05 16:15:54","location":"OBRUK-BOR (NIGDE)","lat":"37.9852","lng":"34.1072","mag":"2.3","depth":"1.4"},{"date":"2020.10.05 17:55:09","location":"YUNANISTAN","lat":"39.9362","lng":"24.3797","mag":"3.9","depth":"8.2"},{"date":"2020.10.05 17:57:52","location":"YUNANISTAN","lat":"39.8580","lng":"23.5578","mag":"4.1","depth":"15.1"},{"date":"2020.10.05 18:22:35","location":"DENIZKOY-DIKILI (IZMIR)","lat":"38.9602","lng":"26.6958","mag":"2.1","depth":"13.3"},{"date":"2020.10.05 18:27:13","location":"KUMRALI-MERAM (KONYA)","lat":"37.7067","lng":"32.2600","mag":"1.2","depth":"9.5"},{"date":"2020.10.05 18:30:37","location":"YALI-BODRUM (MUGLA)","lat":"36.9868","lng":"27.3670","mag":"1.8","depth":"9.4"},{"date":"2020.10.05 18:47:43","location":"BAKIRTOLU-KARATAY (KONYA)","lat":"37.8352","lng":"32.7012","mag":"1.6","depth":"4.8"},{"date":"2020.10.05 19:12:17","location":"GUNDEGER-PUTURGE (MALATYA)","lat":"38.2875","lng":"38.8428","mag":"3.4","depth":"1.5"},{"date":"2020.10.05 19:39:47","location":"MARMARA DENIZI","lat":"40.8062","lng":"28.0427","mag":"2.2","depth":"13.7"},{"date":"2020.10.05 20:27:16","location":"AKDENIZ","lat":"35.8035","lng":"28.2677","mag":"2.0","depth":"7.9"},{"date":"2020.10.05 20:35:40","location":"DINARBEY-YEDISU (BINGOL)","lat":"39.3487","lng":"40.6935","mag":"2.3","depth":"5.8"},{"date":"2020.10.05 22:10:31","location":"AZERBAYCAN","lat":"41.1245","lng":"44.0502","mag":"3.3","depth":"5.0"},{"date":"2020.10.05 22:53:00","location":"VAN GOLU","lat":"38.7085","lng":"43.0705","mag":"1.8","depth":"19.4"},{"date":"2020.10.05 23:20:36","location":"AKDENIZ","lat":"36.5448","lng":"28.8042","mag":"2.0","depth":"12.7"},{"date":"2020.10.05 23:35:35","location":"GUNLUCE-EMET (KUTAHYA)","lat":"39.4250","lng":"29.2890","mag":"1.3","depth":"10.3"},{"date":"2020.10.05 23:50:26","location":"GIRIT ADASI ACIKLARI (AKDENIZ)","lat":"34.4287","lng":"25.3138","mag":"3.4","depth":"86.3"},{"date":"2020.10.06 00:54:12","location":"KATRANCI-YATAGAN (MUGLA)","lat":"37.3778","lng":"27.9392","mag":"1.3","depth":"5.0"},{"date":"2020.10.06 00:58:48","location":"AKDENIZ","lat":"35.8318","lng":"28.2372","mag":"1.3","depth":"5.0"},{"date":"2020.10.06 01:04:20","location":"HISARONU-MARMARIS (MUGLA)","lat":"36.7918","lng":"28.1038","mag":"0.6","depth":"21.0"},{"date":"2020.10.06 02:38:18","location":"AKDENIZ","lat":"35.8093","lng":"28.2200","mag":"1.2","depth":"5.0"},{"date":"2020.10.06 02:45:55","location":"AKDENIZ","lat":"35.8217","lng":"28.2205","mag":"2.0","depth":"5.0"},{"date":"2020.10.06 03:18:08","location":"AKDENIZ","lat":"35.0553","lng":"30.7832","mag":"2.3","depth":"30.2"},{"date":"2020.10.06 03:31:26","location":"AKDENIZ","lat":"35.4710","lng":"29.5598","mag":"1.6","depth":"8.6"},{"date":"2020.10.06 04:38:24","location":"KUSADASI (AYDIN)","lat":"37.8315","lng":"27.2643","mag":"2.2","depth":"5.4"},{"date":"2020.10.06 04:42:41","location":"YAYLIYAKA-(VAN)","lat":"38.8273","lng":"43.3642","mag":"1.5","depth":"13.5"},{"date":"2020.10.06 04:46:29","location":"DOGANYUVA-CAYIRLI (ERZINCAN)","lat":"39.8593","lng":"39.8775","mag":"2.3","depth":"8.3"},{"date":"2020.10.06 04:46:31","location":"YENIKOY-KUSADASI (AYDIN)","lat":"37.8367","lng":"27.3302","mag":"1.5","depth":"4.9"},{"date":"2020.10.06 05:54:13","location":"BOZBURUN-MARMARIS (MUGLA)","lat":"36.7212","lng":"28.0283","mag":"1.0","depth":"19.1"},{"date":"2020.10.06 06:03:59","location":"ERGIN-LICE (DIYARBAKIR)","lat":"38.4988","lng":"40.5453","mag":"2.0","depth":"8.9"},{"date":"2020.10.06 06:06:41","location":"AKDENIZ","lat":"35.8950","lng":"28.1950","mag":"2.2","depth":"5.0"},{"date":"2020.10.06 06:06:58","location":"YESILPINAR-HEKIMHAN (MALATYA)","lat":"38.7253","lng":"38.0600","mag":"1.2","depth":"13.4"},{"date":"2020.10.06 06:18:45","location":"CANDARLI KORFEZI (EGE DENIZI)","lat":"38.8173","lng":"26.8940","mag":"1.6","depth":"6.3"},{"date":"2020.10.06 06:19:13","location":"GULPINAR ACIKLARI-CANAKKALE (EGE DENIZI)","lat":"39.4828","lng":"25.8268","mag":"1.8","depth":"6.8"},{"date":"2020.10.06 06:47:54","location":"ALICAN-YAZIHAN (MALATYA)","lat":"38.6912","lng":"38.0557","mag":"1.2","depth":"8.3"},{"date":"2020.10.06 07:04:00","location":"YUNANISTAN","lat":"40.3245","lng":"24.0580","mag":"1.9","depth":"5.0"},{"date":"2020.10.06 08:50:18","location":"OBRUK-BOR (NIGDE)","lat":"37.9900","lng":"34.0842","mag":"3.0","depth":"5.0"},{"date":"2020.10.06 09:16:35","location":"GOKOVA KORFEZI (AKDENIZ)","lat":"36.9478","lng":"27.7045","mag":"2.7","depth":"6.7"},{"date":"2020.10.06 09:30:49","location":"AKDENIZ REVIZE01 (2020.10.06 09:30:49)","lat":"36.7968","lng":"26.4960","mag":"2.2","depth":"19.0"},{"date":"2020.10.06 10:23:25","location":"ARPADERE-KINIK (IZMIR)","lat":"38.9868","lng":"27.4905","mag":"1.5","depth":"17.7"},{"date":"2020.10.06 10:28:59","location":"KAYABASI-KEMAH (ERZINCAN)","lat":"39.5303","lng":"38.6770","mag":"2.6","depth":"9.1"},{"date":"2020.10.06 11:36:43","location":"AVDAN-SOMA (MANISA)","lat":"39.1472","lng":"27.5358","mag":"1.5","depth":"0.0"},{"date":"2020.10.06 11:58:30","location":"AKTARLI-PUTURGE (MALATYA)","lat":"38.2667","lng":"38.8245","mag":"3.5","depth":"1.4"},{"date":"2020.10.06 12:05:24","location":"CAKIROGLU-MADEN (ELAZIG)","lat":"38.3372","lng":"39.3630","mag":"1.8","depth":"26.4"},{"date":"2020.10.06 12:15:45","location":"PELITLI-GEBZE (KOCAELI)","lat":"40.8343","lng":"29.4665","mag":"1.2","depth":"0.0"},{"date":"2020.10.06 12:24:22","location":"CAYBUKU-(MUGLA)","lat":"37.2205","lng":"28.1743","mag":"1.7","depth":"0.0"},{"date":"2020.10.06 12:29:18","location":"KUCUKCAMILI-BALA (ANKARA)","lat":"39.3452","lng":"33.4168","mag":"1.8","depth":"0.0"},{"date":"2020.10.06 12:30:54","location":"OZLUCE-(MUGLA)","lat":"37.2637","lng":"28.4532","mag":"1.4","depth":"22.3"}]