[{"date":"2021.10.07 09:34:12","location":"YESILOVA-MUSTAFAKEMALPASA (BURSA)","lat":"40.1268","lng":"28.4483","mag":"1.4","depth":"11.5"},{"date":"2021.10.07 09:53:00","location":"CAKALLIK-SERIK (ANTALYA)","lat":"36.9078","lng":"30.9715","mag":"1.5","depth":"8.6"},{"date":"2021.10.07 10:05:18","location":"DEGIRMENCIELI-KINIK (IZMIR)","lat":"39.0883","lng":"27.4667","mag":"1.9","depth":"0.0"},{"date":"2021.10.07 10:57:29","location":"YENIPINAR-HISARCIK (KUTAHYA)","lat":"39.2122","lng":"29.1717","mag":"2.6","depth":"3.0"},{"date":"2021.10.07 11:21:20","location":"BUCA (IZMIR)","lat":"38.4118","lng":"27.1865","mag":"2.0","depth":"19.1"},{"date":"2021.10.07 11:26:20","location":"KIRANYER-BABADAG (DENIZLI)","lat":"37.7922","lng":"28.7917","mag":"2.0","depth":"5.5"},{"date":"2021.10.07 11:30:03","location":"IMAMUSAGI-SILIFKE (MERSIN)","lat":"36.2930","lng":"33.7490","mag":"1.1","depth":"0.0"},{"date":"2021.10.07 12:05:38","location":"HERSEK-ALTINOVA (YALOVA)","lat":"40.7418","lng":"29.5462","mag":"1.2","depth":"0.0"},{"date":"2021.10.07 12:15:28","location":"OLUCAK-(AFYONKARAHISAR)","lat":"38.9148","lng":"30.1865","mag":"2.2","depth":"16.0"},{"date":"2021.10.07 12:43:45","location":"FINDIKLI-ORHANGAZI (BURSA)","lat":"40.4908","lng":"29.2668","mag":"1.0","depth":"0.0"},{"date":"2021.10.07 13:08:25","location":"ONIKI ADALAR (AKDENIZ)","lat":"36.5212","lng":"27.1582","mag":"1.9","depth":"16.0"},{"date":"2021.10.07 13:08:44","location":"YAMACOBA-SEHITKAMIL (GAZIANTEP)","lat":"37.1703","lng":"37.1080","mag":"1.9","depth":"0.0"},{"date":"2021.10.07 13:24:15","location":"KALETEPE-KIRIKHAN (HATAY)","lat":"36.6468","lng":"36.6127","mag":"1.8","depth":"17.2"},{"date":"2021.10.07 13:38:03","location":"HELVA-(BAYBURT)","lat":"40.1552","lng":"40.4770","mag":"2.4","depth":"2.4"},{"date":"2021.10.07 14:00:22","location":"CAYIRLI-(NIGDE)","lat":"38.0780","lng":"34.9955","mag":"1.6","depth":"13.5"},{"date":"2021.10.07 14:51:20","location":"MENDERES-BEYDAG (IZMIR)","lat":"38.0927","lng":"28.2060","mag":"1.2","depth":"21.9"},{"date":"2021.10.07 15:00:39","location":"AKDENIZ","lat":"36.0268","lng":"28.2815","mag":"1.9","depth":"6.2"},{"date":"2021.10.07 15:05:50","location":"YESILOVACIK-SILIFKE (MERSIN)","lat":"36.1972","lng":"33.7053","mag":"1.4","depth":"0.0"},{"date":"2021.10.07 15:16:00","location":"KIZIRYURDU-SUSEHRI (SIVAS)","lat":"40.1005","lng":"38.1238","mag":"2.2","depth":"7.8"},{"date":"2021.10.07 17:02:09","location":"GOKCEAHMET-AKHISAR (MANISA)","lat":"39.0095","lng":"27.8627","mag":"2.0","depth":"11.2"},{"date":"2021.10.07 18:25:03","location":"CENDIK-(BURDUR)","lat":"37.7057","lng":"30.1490","mag":"2.6","depth":"5.0"},{"date":"2021.10.07 18:56:09","location":"ONIKI ADALAR (AKDENIZ)","lat":"36.2827","lng":"27.1668","mag":"1.8","depth":"12.1"},{"date":"2021.10.07 19:59:47","location":"GIRIT ADASI (AKDENIZ)","lat":"35.1140","lng":"25.3258","mag":"2.6","depth":"7.5"},{"date":"2021.10.07 20:24:24","location":"BADEMLI-AYVACIK (CANAKKALE)","lat":"39.5052","lng":"26.1777","mag":"2.4","depth":"2.8"},{"date":"2021.10.07 20:25:39","location":"SISAM ADASI (EGE DENIZI)","lat":"37.7290","lng":"26.9250","mag":"1.5","depth":"20.4"},{"date":"2021.10.07 21:12:30","location":"HASANCAVUSLAR-TIRE (IZMIR)","lat":"38.0587","lng":"27.5065","mag":"1.9","depth":"5.6"},{"date":"2021.10.07 22:15:55","location":"KOCAOZ-COBANLAR (AFYONKARAHISAR)","lat":"38.7178","lng":"30.8285","mag":"1.3","depth":"5.0"},{"date":"2021.10.07 23:16:32","location":"GIRIT ADASI (AKDENIZ)","lat":"35.1277","lng":"24.1958","mag":"2.7","depth":"5.1"},{"date":"2021.10.07 23:18:03","location":"GIRIT ADASI (AKDENIZ)","lat":"35.1282","lng":"25.3095","mag":"2.0","depth":"5.4"},{"date":"2021.10.07 23:27:10","location":"CARDAK (DENIZLI)","lat":"37.8143","lng":"29.6817","mag":"1.3","depth":"8.3"},{"date":"2021.10.08 00:10:47","location":"ATAKOY-MENDERES (IZMIR)","lat":"38.0512","lng":"27.1185","mag":"1.5","depth":"7.3"},{"date":"2021.10.08 00:22:39","location":"AKDENIZ","lat":"36.1335","lng":"27.6605","mag":"2.0","depth":"12.0"},{"date":"2021.10.08 00:40:34","location":"KUSADASI KORFEZI (EGE DENIZI)","lat":"37.8905","lng":"26.8607","mag":"1.6","depth":"10.0"},{"date":"2021.10.08 00:49:17","location":"GUNEYKOY-SIVRICE (ELAZIG)","lat":"38.5152","lng":"39.3352","mag":"2.1","depth":"10.4"},{"date":"2021.10.08 01:11:01","location":"ONIKI ADALAR (AKDENIZ)","lat":"36.4420","lng":"27.0762","mag":"2.6","depth":"4.0"},{"date":"2021.10.08 01:21:15","location":"KUSADASI KORFEZI (EGE DENIZI)","lat":"37.8905","lng":"26.8882","mag":"2.1","depth":"7.1"},{"date":"2021.10.08 01:23:38","location":"GIRIT ADASI (AKDENIZ)","lat":"35.1230","lng":"25.2895","mag":"1.9","depth":"6.6"},{"date":"2021.10.08 01:28:25","location":"GIRIT ADASI (AKDENIZ)","lat":"35.1500","lng":"25.2468","mag":"2.4","depth":"12.3"},{"date":"2021.10.08 01:47:17","location":"KUSADASI KORFEZI (EGE DENIZI)","lat":"37.8483","lng":"27.0265","mag":"1.6","depth":"5.3"},{"date":"2021.10.08 02:05:24","location":"NASA-SIMAV (KUTAHYA)","lat":"39.1543","lng":"28.9822","mag":"2.1","depth":"7.6"},{"date":"2021.10.08 02:14:29","location":"MEYDANCIK-(VAN)","lat":"38.7663","lng":"43.4943","mag":"1.2","depth":"20.1"},{"date":"2021.10.08 02:48:20","location":"GIRIT ADASI (AKDENIZ)","lat":"35.2300","lng":"26.1535","mag":"1.9","depth":"6.9"},{"date":"2021.10.08 03:09:23","location":"GIRIT ADASI (AKDENIZ)","lat":"35.0910","lng":"25.2495","mag":"2.3","depth":"5.5"},{"date":"2021.10.08 03:35:56","location":"SERINYAKA-GUNDOGMUS (ANTALYA)","lat":"36.8217","lng":"31.8032","mag":"1.5","depth":"12.5"},{"date":"2021.10.08 04:33:54","location":"GULLUK KORFEZI (EGE DENIZI)","lat":"37.1267","lng":"27.4253","mag":"1.2","depth":"3.2"},{"date":"2021.10.08 04:56:34","location":"MUSALIKALESI-AKDAGMADENI (YOZGAT)","lat":"39.7472","lng":"35.8067","mag":"1.5","depth":"17.3"},{"date":"2021.10.08 05:39:47","location":"HASKOY-SARAYKOY (DENIZLI)","lat":"37.9317","lng":"28.8818","mag":"1.5","depth":"10.5"},{"date":"2021.10.08 06:06:15","location":"GIRIT ADASI (AKDENIZ)","lat":"35.2997","lng":"25.2817","mag":"2.3","depth":"8.4"},{"date":"2021.10.08 06:14:37","location":"GIRIT ADASI (AKDENIZ)","lat":"35.2258","lng":"25.2602","mag":"2.1","depth":"9.6"},{"date":"2021.10.08 06:20:35","location":"GIRIT ADASI (AKDENIZ)","lat":"35.1848","lng":"25.2788","mag":"2.1","depth":"7.1"},{"date":"2021.10.08 06:27:47","location":"GIRIT ADASI (AKDENIZ)","lat":"35.0757","lng":"25.2790","mag":"2.3","depth":"9.1"},{"date":"2021.10.08 06:36:09","location":"GIRIT ADASI (AKDENIZ)","lat":"35.1645","lng":"25.2242","mag":"2.9","depth":"13.0"},{"date":"2021.10.08 07:21:06","location":"GIRIT ADASI (AKDENIZ)","lat":"35.1060","lng":"25.2400","mag":"2.4","depth":"3.6"},{"date":"2021.10.08 07:32:18","location":"KAPAKLI-(BURDUR)","lat":"37.4325","lng":"30.3432","mag":"2.3","depth":"12.3"},{"date":"2021.10.08 07:33:55","location":"AKDENIZ","lat":"35.6522","lng":"28.9697","mag":"2.3","depth":"80.1"},{"date":"2021.10.08 07:49:42","location":"GIRIT ADASI (AKDENIZ)","lat":"34.9138","lng":"25.2638","mag":"1.9","depth":"7.3"}]